Multimodal_AUV/__init__.py
Multimodal_AUV/cli.py
Multimodal_AUV/config/__init__.py
Multimodal_AUV/config/paths.py
Multimodal_AUV/data/__init__.py
Multimodal_AUV/data/datasets.py
Multimodal_AUV/data/loaders.py
Multimodal_AUV/data_preparation/__init__.py
Multimodal_AUV/data_preparation/GAVIA_auv_image_processing.py
Multimodal_AUV/data_preparation/geospatial.py
Multimodal_AUV/data_preparation/image_processing.py
Multimodal_AUV/data_preparation/main_data_preparation.py
Multimodal_AUV/data_preparation/utilities.py
Multimodal_AUV/Examples/__init__.py
Multimodal_AUV/Examples/Example training with image noise.py
Multimodal_AUV/Examples/Example training with image noise_safe.py
Multimodal_AUV/Examples/Example unimodal training with image noise.py
Multimodal_AUV/Examples/Example_data_preparation.py
Multimodal_AUV/Examples/Example_Inference_model.py
Multimodal_AUV/Examples/Example_Retraining_model.py
Multimodal_AUV/Examples/Example_training_from_scratch.py
Multimodal_AUV/functions/__init__.py
Multimodal_AUV/functions/functions.py
Multimodal_AUV/inference/__init__.py
Multimodal_AUV/inference/inference_data.py
Multimodal_AUV/inference/predictors.py
Multimodal_AUV/main.py
Multimodal_AUV/models/__init__.py
Multimodal_AUV/models/base_models.py
Multimodal_AUV/models/model_utils.py
Multimodal_AUV/train/__init__.py
Multimodal_AUV/train/checkpointing.py
Multimodal_AUV/train/loop_utils.py
Multimodal_AUV/train/multimodal.py
Multimodal_AUV/train/unimodal.py
Multimodal_AUV/utils/__init__.py
Multimodal_AUV/utils/device.py
multimodal_auv-0.1.0.dist-info/entry_points.txt
multimodal_auv-0.1.0.dist-info/LICENSE
multimodal_auv-0.1.0.dist-info/METADATA
multimodal_auv-0.1.0.dist-info/WHEEL
multimodal_auv-0.1.0.dist-info/RECORD
