Metadata-Version: 2.3
Name: multimodal-auv
Version: 0.1.0
Summary: Multimodal AUV Bayesian Neural Networks for Underwater Environmental Understanding
License: MIT
Keywords: AUV,Bayesian Neural Networks,Underwater Mapping,Habitat Classification,Multimodal Data,Oceanography,geospatial-data,environmental-monitoring,uncertainty-quantification,computer-vision,remote-sensing
Author: Tom Morgan
Author-email: phd01tm@sams.ac.uk
Requires-Python: >=3.9,<3.10
Classifier: Development Status :: 4 - Beta
Classifier: Intended Audience :: Science/Research
Classifier: License :: OSI Approved :: MIT License
Classifier: Operating System :: OS Independent
Classifier: Programming Language :: Python :: 3
Classifier: Programming Language :: Python :: 3.9
Classifier: Topic :: Scientific/Engineering :: Artificial Intelligence
Classifier: Topic :: Scientific/Engineering :: Oceanography
Classifier: Topic :: Software Development :: Libraries :: Python Modules
Requires-Dist: absl-py (>=2.1.0,<3.0.0)
Requires-Dist: affine (>=2.3.0,<3.0.0)
Requires-Dist: bayesian-torch (>=0.5.0,<0.6.0)
Requires-Dist: click (>=8.1.8,<9.0.0)
Requires-Dist: fsspec (>=2024.6.1,<2025.0.0)
Requires-Dist: huggingface_hub (>=0.31.2,<0.32.0)
Requires-Dist: imageio (>=2.37.0,<3.0.0)
Requires-Dist: joblib (>=1.4.2,<2.0.0)
Requires-Dist: matplotlib (>=3.9.2,<4.0.0)
Requires-Dist: numpy (==1.26.4)
Requires-Dist: opencv-python (>=4.11.0.86,<5.0.0.0)
Requires-Dist: pandas (>=2.2.3,<3.0.0)
Requires-Dist: pillow (>=11.0.0,<12.0.0)
Requires-Dist: pynvml (>=12.0.0,<13.0.0)
Requires-Dist: pyproj (>=3.6.1,<4.0.0)
Requires-Dist: rasterio (>=1.4.3,<2.0.0)
Requires-Dist: requests (>=2.32.4,<3.0.0)
Requires-Dist: scikit-image (>=0.24.0,<0.25.0)
Requires-Dist: scikit-learn (==1.6.1)
Requires-Dist: scipy (==1.13.1)
Requires-Dist: torch (>=2.0,<3.0)
Requires-Dist: tqdm (>=4.67.1,<5.0.0)
Requires-Dist: utm (>=0.8.1,<0.9.0)
Project-URL: Documentation, https://github.com/sams-tom/Multimodal-AUV/blob/master/README.md
Project-URL: Homepage, https://github.com/sams-tom/Multimodal-AUV
Project-URL: Repository, https://github.com/sams-tom/Multimodal-AUV
